django_user_assets-0.1.5.dist-info/DESCRIPTION.rst
django_user_assets-0.1.5.dist-info/METADATA
django_user_assets-0.1.5.dist-info/RECORD
django_user_assets-0.1.5.dist-info/WHEEL
django_user_assets-0.1.5.dist-info/metadata.json
django_user_assets-0.1.5.dist-info/top_level.txt
user_assets/__init__.py
user_assets/admin.py
user_assets/apps.py
user_assets/context_processors.py
user_assets/models.py
user_assets/migrations/0001_initial.py
user_assets/migrations/__init__.py
