Metadata-Version: 2.0
Name: django-user-assets
Version: 0.1.5
Summary: Allow users to create site assets with django admin
Home-page: https://github.com/idaproject/django-user-assets
Author: Arseny Sysolyatin
Author-email: arseny.sysolyatin@gmail.com
License: MIT
Keywords: django-user-assets
Platform: UNKNOWN
Classifier: Development Status :: 3 - Alpha
Classifier: Framework :: Django
Classifier: Framework :: Django :: 1.8
Classifier: Framework :: Django :: 1.9
Classifier: Framework :: Django :: 1.10
Classifier: Intended Audience :: Developers
Classifier: License :: OSI Approved :: BSD License
Classifier: Natural Language :: English
Classifier: Programming Language :: Python :: 3
Classifier: Programming Language :: Python :: 3.3
Classifier: Programming Language :: Python :: 3.4
Classifier: Programming Language :: Python :: 3.5
Requires-Dist: Django (>=1.8)
Requires-Dist: django-admin-sortable2 (>=0.6.16)
